[{"id":"1234245","title":"A Book","imageUrl":"https://www.publicbooks.org/wp-content/uploads/2017/01/book-e1484158615982.jpg","description":"This is an awesome book!","price":"19"},{"title":"Another Product","imageUrl":"https://upload.wikimedia.org/wikipedia/commons/thumb/b/b6/Gutenberg_Bible%2C_Lenox_Copy%2C_New_York_Public_Library%2C_2009._Pic_01.jpg/330px-Gutenberg_Bible%2C_Lenox_Copy%2C_New_York_Public_Library%2C_2009._Pic_01.jpg","description":"Another very amazing product!","price":"20.99","id":"0.6583411841387365"}]